dvplx/__init__.py
dvplx/cmd.py
dvplx/color.py
dvplx/converter.py
dvplx/dvpl.py
dvplx-1.2.3.dist-info/METADATA
dvplx-1.2.3.dist-info/WHEEL
dvplx-1.2.3.dist-info/entry_points.txt
dvplx-1.2.3.dist-info/licenses/LICENSE
dvplx-1.2.3.dist-info/RECORD
