Metadata-Version: 2.1
Name: dvplx
Version: 1.2.3
Summary: A CLI Tool Coded In Python To Convert WoTB ( Dava ) SmartDLC DVPL File Based On LZ4 High Compression.
Project-URL: Homepage, https://github.com/rifsxd/dvplx
Author-email: RifsxD <support@rxd-mods.xyz>
License: MIT License
License-File: LICENSE
Classifier: Environment :: Console
Classifier: License :: OSI Approved :: MIT License
Classifier: Operating System :: OS Independent
Classifier: Programming Language :: Python :: 3
Requires-Python: >=3.10
Requires-Dist: lz4>=4.3.3
